CHANGES.md
INSTALL.txt
MANIFEST.in
README.txt
VERSION.txt
pyproject.toml
setup.cfg
setup.py
demos/colors/colortest.py
demos/gadflypaper/00readme.txt
demos/gadflypaper/gfe.py
demos/odyssey/00readme.txt
demos/odyssey/dodyssey.py
demos/odyssey/fodyssey.py
demos/odyssey/odyssey.py
demos/odyssey/odyssey.txt
demos/rlzope/readme.txt
demos/rlzope/rlzope.py
demos/stdfonts/00readme.txt
demos/stdfonts/stdfonts.py
demos/tests/testdemos.py
docs/00readme.txt
docs/Makefile
docs/genAll.py
docs/gen_epydoc
docs/make.bat
docs/images/Edit_Prefs.gif
docs/images/Python_21.gif
docs/images/Python_21_HINT.gif
docs/images/fileExchange.gif
docs/images/jpn.gif
docs/images/jpnchars.jpg
docs/images/lj8100.jpg
docs/images/redsquare.png
docs/images/replogo.a85
docs/images/replogo.gif
docs/images/testimg.gif
docs/reference/build.bat
docs/reference/genreference.py
docs/reference/reference.yml
docs/source/conf.py
docs/source/graphics.rst
docs/source/index.rst
docs/source/lib.rst
docs/source/pdfgen.rst
docs/source/platypus.rst
docs/source/_static/basic.css
docs/source/_static/default.css
docs/source/_templates/layout.html
docs/source/_templates/page.html
docs/userguide/app_demos.py
docs/userguide/ch1_intro.py
docs/userguide/ch2_graphics.py
docs/userguide/ch2a_fonts.py
docs/userguide/ch3_pdffeatures.py
docs/userguide/ch4_platypus_concepts.py
docs/userguide/ch5_paragraphs.py
docs/userguide/ch6_tables.py
docs/userguide/ch7_custom.py
docs/userguide/genuserguide.py
docs/userguide/graph_charts.py
docs/userguide/graph_concepts.py
docs/userguide/graph_intro.py
docs/userguide/graph_shapes.py
docs/userguide/graph_widgets.py
docs/userguide/testfile.txt
src/reportlab/MANIFEST.in
src/reportlab/__init__.py
src/reportlab/rl_config.py
src/reportlab/rl_settings.py
src/reportlab/fonts/00readme.txt
src/reportlab/fonts/DarkGarden-changelog.txt
src/reportlab/fonts/DarkGarden-copying-gpl.txt
src/reportlab/fonts/DarkGarden-copying.txt
src/reportlab/fonts/DarkGarden-readme.txt
src/reportlab/fonts/DarkGarden.sfd
src/reportlab_qpython.egg-info/PKG-INFO
src/reportlab_qpython.egg-info/SOURCES.txt
src/reportlab_qpython.egg-info/dependency_links.txt
src/reportlab_qpython.egg-info/requires.txt
src/reportlab_qpython.egg-info/top_level.txt
