Metadata-Version: 2.4
Name: reportlab-qpython
Version: 4.3.1.1
Summary: The Reportlab Toolkit
Home-page: https://qpypi.qpython.org/project/reportlab-qpython/
Author: The QPYPI Team
Author-email: qpypi@qpython.org
License: BSD license (see license.txt for details), Copyright (c) 2000-2025, ReportLab Inc.
Classifier: Intended Audience :: Developers
Classifier: Intended Audience :: Education
Classifier: Intended Audience :: Information Technology
Classifier: Intended Audience :: End Users/Desktop
Classifier: License :: OSI Approved :: Apache Software License
Classifier: Operating System :: Android
Classifier: Programming Language :: Python
Classifier: Programming Language :: Python :: 3.12
Classifier: Topic :: Software Development
Requires-Python: ==3.12.*
Requires-Dist: pillow-qpython
Requires-Dist: chardet
Provides-Extra: accel
Requires-Dist: rl_accel<1.1,>=0.9.0; extra == "accel"
Provides-Extra: renderpm
Requires-Dist: rl_renderPM<4.1,>=4.0.3; extra == "renderpm"
Provides-Extra: pycairo
Requires-Dist: rlPyCairo<1,>=0.2.0; extra == "pycairo"
Requires-Dist: freetype-py<2.4,>=2.3.0; extra == "pycairo"
Dynamic: author
Dynamic: author-email
Dynamic: classifier
Dynamic: description
Dynamic: description-content-type
Dynamic: home-page
Dynamic: license
Dynamic: provides-extra
Dynamic: requires-dist
Dynamic: requires-python
Dynamic: summary
